cdk_cloudformation_netapp_fsxn_exportpolicy/__init__.py
cdk_cloudformation_netapp_fsxn_exportpolicy/py.typed
cdk_cloudformation_netapp_fsxn_exportpolicy/_jsii/__init__.py
cdk_cloudformation_netapp_fsxn_exportpolicy/_jsii/netapp-fsxn-exportpolicy@1.0.0-alpha.7.jsii.tgz
cdk_cloudformation_netapp_fsxn_exportpolicy-1.0.0a7.dist-info/LICENSE
cdk_cloudformation_netapp_fsxn_exportpolicy-1.0.0a7.dist-info/METADATA
cdk_cloudformation_netapp_fsxn_exportpolicy-1.0.0a7.dist-info/WHEEL
cdk_cloudformation_netapp_fsxn_exportpolicy-1.0.0a7.dist-info/top_level.txt
cdk_cloudformation_netapp_fsxn_exportpolicy-1.0.0a7.dist-info/RECORD
